dnasim/__init__.py
dnasim-0.0.1.dist-info/LICENSE.txt
dnasim-0.0.1.dist-info/METADATA
dnasim-0.0.1.dist-info/WHEEL
dnasim-0.0.1.dist-info/top_level.txt
dnasim-0.0.1.dist-info/RECORD
